arcipelago/__init__.py
arcipelago/db.py
arcipelago/edit_conv.py
arcipelago/event.py
arcipelago/event_conv.py
arcipelago/extra/gcalendar.py
arcipelago/init_db.py
arcipelago/main.py
arcipelago/notification.py
arcipelago-0.1.0.dist-info/METADATA
arcipelago-0.1.0.dist-info/WHEEL
arcipelago-0.1.0.dist-info/RECORD
